multiclass_cascade_classifier/Scripts.py
multiclass_cascade_classifier/Skeleton.py
multiclass_cascade_classifier/__init__.py
multiclass_cascade_classifier/predict.py
multiclass_cascade_classifier/split.py
multiclass_cascade_classifier/test.py
multiclass_cascade_classifier/train.py
multiclass_cascade_classifier/base/ClassifierHelper.py
multiclass_cascade_classifier/base/DataFrameNormalizer.py
multiclass_cascade_classifier/base/DataHelper.py
multiclass_cascade_classifier/base/DataPredicter.py
multiclass_cascade_classifier/base/DataTrainer.py
multiclass_cascade_classifier/base/DataVectorizer.py
multiclass_cascade_classifier/base/FeaturesManipulator.py
multiclass_cascade_classifier/base/HyperSelector.py
multiclass_cascade_classifier/base/LogJournal.py
multiclass_cascade_classifier/base/MetricsGenerator.py
multiclass_cascade_classifier/base/PreProcessing.py
multiclass_cascade_classifier/base/VariablesChecker.py
multiclass_cascade_classifier/base/__init__.py
multiclass_cascade_classifier/base/variables/Variables.py
multiclass_cascade_classifier/base/variables/__init__.py
multiclass_cascade_classifier-1.0.14.dist-info/LICENSE
multiclass_cascade_classifier-1.0.14.dist-info/METADATA
multiclass_cascade_classifier-1.0.14.dist-info/WHEEL
multiclass_cascade_classifier-1.0.14.dist-info/entry_points.txt
multiclass_cascade_classifier-1.0.14.dist-info/top_level.txt
multiclass_cascade_classifier-1.0.14.dist-info/RECORD
