Metadata-Version: 2.1
Name: multiclass-cascade-classifier
Version: 1.0.14
Summary: This package implements a multiclass cascade classifier for text classification in the contexte of web-scraping.
Home-page: https://github.com/Thomasaujoux/multiclass_cascade_classifier
Author: ThomasAujoux
Author-email: ThomasAujoux <thomas.aujoux@gmail.com>
Project-URL: Homepage, https://github.com/Thomasaujoux/multiclass_cascade_classifier
Project-URL: Bug Tracker, https://github.com/Thomasaujoux/multiclass_cascade_classifier/wiki
Classifier: Programming Language :: Python :: 3
Requires-Python: >=3.7
License-File: LICENSE
Requires-Dist: click ==8.1.7
Requires-Dist: joblib ==1.3.1
Requires-Dist: nltk ==3.8.1
Requires-Dist: pandas ==2.0.3
Requires-Dist: PyYAML ==6.0.1
Requires-Dist: scikit-learn ==1.3.0
Requires-Dist: openpyxl ==3.1.2
